flask_nicely
