Metadata-Version: 1.1
Name: Flask-Nicely
Version: 0.2.0
Summary: Pretty Flask JSON responses for API building.
Home-page: http://github.com/jwpe/flask-nicely/
Author: Jonathan Evans
Author-email: jwpevans@gmail.com
License: BSD
Platform: any
Classifier: Programming Language :: Python
Classifier: Programming Language :: Python :: 3
Classifier: Development Status :: 4 - Beta
Classifier: Natural Language :: English
Classifier: Environment :: Web Environment
Classifier: Intended Audience :: Developers
Classifier: License :: OSI Approved :: BSD License
Classifier: Operating System :: OS Independent
Classifier: Topic :: Software Development :: Libraries :: Python Modules
Classifier: Topic :: Software Development :: Libraries :: Application Frameworks
Classifier: Topic :: Internet :: WWW/HTTP :: Dynamic Content
